{
 "products" : [
  {
   "name" : "LARA MERCADO PAGO PF",
   "price" : "140.00",
   "options" : [
    { "Size" : "30 DIas,3 Mêses,1 Ano" }
   ],
   "image" : "http://res.cloudinary.com/duajg3ah1/image/upload/v1717786976/mercadop_a78bb6.png",
   "description" : "Compre As Melhores Contas Conosco"
  },
  {
   "name" : "LARA MERCADO PAGO PJ",
   "price" : "250.00",
   "options" : [
    { "Size" : "30 DIas,3 Mêses,1 Ano" },
    { "Color" : "Blue,Red" },
       { "OneOfAKind" : true }
   ],
   "image" : "http://res.cloudinary.com/duajg3ah1/image/upload/v1717786976/mercadop_a78bb6.png",
   "description" : "Compre As Melhores Contas Conosco"
  },
  {
   "name" : "LARA RECARGA PAY PF",
   "price" : "190.00",
   "options" : [
    { "Size" : "30 DIas,3 Mêses,1 Ano" }
   ],
   "image" : "http://res.cloudinary.com/duajg3ah1/image/upload/v1717787090/recargapay_iq72wb.png",
   "description" : "Compre As Melhores Contas Conosco"
  },
  {
   "name" : "LARA RECARGA PAY PJ",
   "price" : "320.00",
   "options" : [
    { "Size" : "30 DIas,3 Mêses,1 Ano" }
   ],
   "image" : "http://res.cloudinary.com/duajg3ah1/image/upload/v1717787090/recargapay_iq72wb.png",
   "description" : "Compre As Melhores Contas Conosco"
  },
  {
   "name" : "LARA 99PAY PF",
   "price" : "120.00",
   "options" : [
    { "Size" : "30 DIas,3 Mêses,1 Ano" }
   ],
   "image" : "http://res.cloudinary.com/duajg3ah1/image/upload/v1717787146/99pay_shm97d.webp",
   "description" : "Compre As Melhores Contas Conosco"
  },
  {
   "name" : "LARA SUPER DIGITAL PF",
   "price" : "200.00",
   "options" : [
    { "Size" : "30 DIas,3 Mêses,1 Ano" }
   ],
   "image" : "http://res.cloudinary.com/duajg3ah1/image/upload/v1717787188/superdigital_vg76xs.png",
   "description" : "Compre As Melhores Contas Conosco"
  },
  {
   "name" : "LARA CELCOIN PF",
   "price" : "220.00",
   "options" : [
    { "Size" : "30 DIas,3 Mêses,1 Ano" }
   ],
   "image" : "http://res.cloudinary.com/duajg3ah1/image/upload/v1717787245/celcoin_pszun8.png",
   "description" : "Compre As Melhores Contas Conosco"
  },
  {
   "name" : "LARA ONBANK PF",
   "price" : "190.00",
   "options" : [
    { "Size" : "30 DIas,3 Mêses,1 Ano" }
   ],
   "image" : "https://play-lh.googleusercontent.com/49wzl8POWc_3nNCwFi-sqO_RqJaY2TtQgn8Cf4VzTlUdh21243Di7zK_zYDpOg4yacRp=w240-h480-rw",
   "description" : "Compre As Melhores Contas Conosco"
  },
  {
   "name" : "LARA SUMUMP PF",
   "price" : "150.00",
   "options" : [
    { "Size" : "30 DIas,3 Mêses,1 Ano" }
   ],
   "image" : "http://res.cloudinary.com/duajg3ah1/image/upload/v1717787347/sumump2_h5t9yf.png",
   "description" : "Compre As Melhores Contas Conosco"
  },
  {
   "name" : "LARA VOLTZ PF",
   "price" : "250.00",
   "options" : [
    { "Size" : "30 DIas,3 Mêses,1 Ano" }
   ],
   "image" : "http://res.cloudinary.com/duajg3ah1/image/upload/v1717787369/voltzzbanks_pgbs1m.png",
   "description" : "Compre As Melhores Contas Conosco"
  },
  {
   "name" : "LARA DIMO BANK PF",
   "price" : "230.00",
   "options" : [
    { "Size" : "30 DIas,3 Mêses,1 Ano" }
   ],
   "image" : "http://res.cloudinary.com/duajg3ah1/image/upload/v1717787397/zrobankk_dimo_z16exl.png",
   "description" : "Compre As Melhores Contas Conosco"
  },
  {
   "name" : "LARA VIVO PAY PF",
   "price" : "230.00",
   "options" : [
    { "Size" : "30 DIas,3 Mêses,1 Ano" }
   ],
   "image" : "http://res.cloudinary.com/duajg3ah1/image/upload/v1717787432/vivopay_pvec5u.png",
   "description" : "Compre As Melhores Contas Conosco"
   },
   {
   "name" : "LARA NG CASH PF",
   "price" : "200.00",
   "options" : [
    { "Size" : "30 DIas,3 Mêses,1 Ano" }
   ],
   "image" : "http://res.cloudinary.com/duajg3ah1/image/upload/v1717787451/ngcash1_qzjhpf.webp",
   "description" : "Compre As Melhores Contas Conosco"
   },
   {
   "name" : "LARA BIPA WALLET CRIPTO",
   "price" : "230.00",
   "options" : [
    { "Size" : "30 DIas,3 Mêses,1 Ano" }
    ],
   "image" : "http://res.cloudinary.com/duajg3ah1/image/upload/v1717787474/bipaa_zelmkk.png",
   "description" : "Compre As Melhores Contas Conosco"
    },
    {
   "name" : "LARA AME DIGITAL",
   "price" : "220.00",
   "options" : [
    { "Size" : "30 DIas,3 Mêses,1 Ano" }
    ],
   "image" : "http://res.cloudinary.com/duajg3ah1/image/upload/v1717787500/ame_digital_l2rwpi.png",
   "description" : "Compre As Melhores Contas Conosco"
    },
    {
   "name" : "LARA CAPITUAL PF",
   "price" : "125.00",
   "options" : [
    { "Size" : "30 DIas,3 Mêses,1 Ano" }
    ],
   "image" : "http://res.cloudinary.com/duajg3ah1/image/upload/v1717787533/capituall_kqxzyl.png",
   "description" : "Compre As Melhores Contas Conosco"
    },
    {
   "name" : "LARA BIANANCE PF",
   "price" : "450.00",
   "options" : [
    { "Size" : "30 DIas,3 Mêses,1 Ano" }
    ],
   "image" : "http://res.cloudinary.com/duajg3ah1/image/upload/v1717787568/bianance_g7bqlx.png",
   "description" : "Compre As Melhores Contas Conosco"
    },
    {
   "name" : "LARA ASTROPAY PF",
   "price" : "200.00",
   "options" : [
    { "Size" : "30 DIas,3 Mêses,1 Ano" }
    ],
   "image" : "http://res.cloudinary.com/duajg3ah1/image/upload/v1717787589/astropay_miijbg.png",
   "description" : "Compre As Melhores Contas Conosco"
    },
    {
   "name" : "LARA BANQI PF",
   "price" : "200.00",
   "options" : [
    { "Size" : "30 DIas,3 Mêses,1 Ano" }
    ],
   "image" : "http://res.cloudinary.com/duajg3ah1/image/upload/v1717787609/banquii_f3ysw6.webp",
   "description" : "Compre As Melhores Contas Conosco"
    },
    {
   "name" : "LARA CHAVE PIX CPF ( ESPECIFICO )",
   "price" : "550.00",
   "options" : [
    { "Size" : "30 DIas,3 Mêses,1 Ano" }
    ],
   "image" : "http://res.cloudinary.com/duajg3ah1/image/upload/v1717787666/17174773070278786imagem_olrpsh.png",
   "description" : "Compre As Melhores Contas Conosco"
  }
 ]
}
